Workbook

Sheet README
A1: eToro Group Ltd (NASDAQ: ETOR): audit workbook
A2: Prepared 2026-09-29 by IG Finance (buy-side analysis). Companion to eToro_Competitive_Thesis_2026-09-29.docx. Confidential, for internal discussion.
A4: CONFLICT OF INTEREST: the requester works in IG Group Finance (IG Australia). IG Group is a direct competitor of eToro and is included in the peer set as a benchmark only. It is excluded from the growth-strategy matrix.
A6: Scope
A7: 1. Inputs: every disclosed figure as a hard-coded blue input, with source URL, source type and period.
A8: 2. Historical Build & Ratios: quarterly Q1 2024 to Q2 2026 and annual 2023 to 2025 plus LTM, all formulas. Growth, CAGR, margins, take-rate, NC per funded account, and a stated-vs-recomputed cross-check block (MATCH/FLAG).
A9: 3. Peer Benchmark: eToro vs the six confirmed peers (IG Group, Plus500, Webull, XTB, Trading 212, Swissquote). USD conversion, multiples and growth-adjusted multiples by formula. Also holds moat ratings (analyst inputs).
A10: 4. Valuation & Scenarios: eToro EV range (share-count x cash-credit cases), M&A cross-checks (IG/Freetrade, J. Safra Sarasin/Saxo, eToro/TradeZero), and bull/base/bear.
A11: 5. Audit Log: issues found in the source materials and in this build.
A12: 6. Buffett Scorecard: eight tests with live links to the build. Framed as one investor's published framework, not a claim about what Buffett would conclude.
A14: Limitations, stated plainly
A15: a) The network egress proxy blocked WebFetch for every domain tried (investors.etoro.com, sec.gov, globenewswire, wikipedia and others). Every figure comes from web-search summaries of the cited URLs, not from the primary documents. Each input is graded accordingly. Re-verify against the 20-F and 6-K filings before external use.
... A24: Recalculated with LibreOffice headless. Zero formula errors required before release.

Sheet Inputs
A1: Inputs: disclosed figures (blue). Source = URL summarised via WebSearch (WebFetch blocked). CO = company disclosure; PR = press; AGG = aggregator.
A3: ID | B3: Metric | C3: Value | D3: Unit | E3: Period | F3: Source URL | G3: Type | H3: Note
A4: eToro: quarterly (US$m unless stated)
A5: NC_Q1_24 | B5: Net contribution Q1 2024 | C5: 201 | D5: $m | E5: Q1_24 | F5: https://investors.etoro.com/news-releases/news-release-details/etoro-reports-first-quarter-2025-results | G5: CO
A6: NC_Q3_24 | B6: Net contribution Q3 2024 | C6: 167 | D6: $m | E6: Q3_24 | F6: https://www.nasdaq.com/press-release/etoro-reports-third-quarter-2025-results-2025-11-10 | G6: CO
A7: NC_Q4_24 | B7: Net contribution Q4 2024 | C7: 253 | D7: $m | E7: Q4_24 | F7: https://www.nasdaq.com/press-release/etoro-reports-fourth-quarter-and-full-year-2025-results-2026-02-17 | G7: CO
A8: NC_Q1_25 | B8: Net contribution Q1 2025 | C8: 217 | D8: $m | E8: Q1_25 | F8: https://investors.etoro.com/news-releases/news-release-details/etoro-reports-first-quarter-2025-results | G8: CO
A9: NC_Q2_25 | B9: Net contribution Q2 2025 | C9: 210 | D9: $m | E9: Q2_25 | F9: https://www.nasdaq.com/press-release/etoro-reports-second-quarter-2025-results-2025-08-12 | G9: CO
A10: NC_Q3_25 | B10: Net contribution Q3 2025 | C10: 215 | D10: $m | E10: Q3_25 | F10: https://www.nasdaq.com/press-release/etoro-reports-third-quarter-2025-results-2025-11-10 | G10: CO
A11: NC_Q4_25 | B11: Net contribution Q4 2025 | C11: 227 | D11: $m | E11: Q4_25 | F11: https://www.nasdaq.com/press-release/etoro-reports-fourth-quarter-and-full-year-2025-results-2026-02-17 | G11: CO
A12: NC_Q1_26 | B12: Net contribution Q1 2026 | C12: 258 | D12: $m | E12: Q1_26 | F12: https://www.etoro.com/en-us/news-and-analysis/latest-news/press-release/etoro-reports-q1-2026-results/ | G12: CO
A13: NC_Q2_26 | B13: Net contribution Q2 2026 | C13: 229 | D13: $m | E13: Q2_26 | F13: https://investors.etoro.com/news-releases/news-release-details/etoro-reports-second-quarter-2026-results | G13: CO
A14: EB_Q1_24 | B14: Adj. EBITDA Q1 2024 | C14: 87 | D14: $m | E14: Q1_24 | F14: https://investors.etoro.com/news-releases/news-release-details/etoro-reports-first-quarter-2025-results | G14: CO
A15: EB_Q2_24 | B15: Adj. EBITDA Q2 2024 | C15: 55 | D15: $m | E15: Q2_24 | F15: https://www.nasdaq.com/press-release/etoro-reports-second-quarter-2025-results-2025-08-12 | G15: CO
A16: EB_Q3_24 | B16: Adj. EBITDA Q3 2024 | C16: 55 | D16: $m | E16: Q3_24 | F16: https://www.nasdaq.com/press-release/etoro-reports-third-quarter-2025-results-2025-11-10 | G16: CO
... A27: NI_Q1_25 | B27: GAAP net income Q1 2025 | C27: 60 | D27: $m | E27: Q1_25 | F27: https://investors.etoro.com/news-releases/news-release-details/etoro-reports-first-quarter-2025-results | G27: CO
A28: NI_Q2_25 | B28: GAAP net income Q2 2025 | C28: 30.2 | D28: $m | E28: Q2_25 | F28: https://www.nasdaq.com/press-release/etoro-reports-second-quarter-2025-results-2025-08-12 | G28: CO | H28: Q2 25 includes $15m IPO costs
A29: NI_Q3_25 | B29: GAAP net income Q3 2025 | C29: 57 | D29: $m | E29: Q3_25 | F29: https://www.nasdaq.com/press-release/etoro-reports-third-quarter-2025-results-2025-11-10 | G29: CO
A30: NI_Q1_26 | B30: GAAP net income Q1 2026 | C30: 82 | D30: $m | E30: Q1_26 | F30: https://www.etoro.com/en-us/news-and-analysis/latest-news/press-release/etoro-reports-q1-2026-results/ | G30: CO
A31: NI_Q2_26 | B31: GAAP net income Q2 2026 | C31: 53 | D31: $m | E31: Q2_26 | F31: https://investors.etoro.com/news-releases/news-release-details/etoro-reports-second-quarter-2026-results | G31: CO
A32: FA_Q3_24 | B32: Funded accounts Q3 2024 | C32: 3.21 | D32: m | E32: Q3_24 | F32: https://investors.etoro.com/news-releases (quarterly results; via search summaries) | G32: CO
A33: FA_Q1_25 | B33: Funded accounts Q1 2025 | C33: 3.58 | D33: m | E33: Q1_25 | F33: https://investors.etoro.com/news-releases (quarterly results; via search summaries) | G33: CO
A34: FA_Q2_25 | B34: Funded accounts Q2 2025 | C34: 3.63 | D34: m | E34: Q2_25 | F34: https://investors.etoro.com/news-releases (quarterly results; via search summaries) | G34: CO
A35: FA_Q3_25 | B35: Funded accounts Q3 2025 | C35: 3.73 | D35: m | E35: Q3_25 | F35: https://investors.etoro.com/news-releases (quarterly results; via search summaries) | G35: CO
A36: FA_Q4_25 | B36: Funded accounts Q4 2025 | C36: 3.85 | D36: m | E36: Q4_25 | F36: https://investors.etoro.com/news-releases (quarterly results; via search summaries) | G36: CO | H36: FY25 press said 3.81m; Q4 release 3.85m (conflict)
A37: FA_Q1_26 | B37: Funded accounts Q1 2026 | C37: 4.02 | D37: m | E37: Q1_26 | F37: https://investors.etoro.com/news-releases (quarterly results; via search summaries) | G37: CO
A38: FA_Q2_26 | B38: Funded accounts Q2 2026 | C38: 4.28 | D38: m | E38: Q2_26 | F38: https://investors.etoro.com/news-releases (quarterly results; via search summaries) | G38: CO
A39: AUA_Q2_25 | B39: AUA Q2 2025 | C39: 17.5 | D39: $bn | E39: Q2_25 | F39: https://investors.etoro.com/news-releases (quarterly results; via search summaries) | G39: CO/AGG
A40: AUA_Q3_25 | B40: AUA Q3 2025 | C40: 20.8 | D40: $bn | E40: Q3_25 | F40: https://investors.etoro.com/news-releases (quarterly results; via search summaries) | G40: CO/AGG | H40: Q3 25 via stocktwits recap (AGG)
A41: AUA_Q4_25 | B41: AUA Q4 2025 | C41: 18.5 | D41: $bn | E41: Q4_25 | F41: https://investors.etoro.com/news-releases (quarterly results; via search summaries) | G41: CO/AGG
A42: AUA_Q1_26 | B42: AUA Q1 2026 | C42: 18.7 | D42: $bn | E42: Q1_26 | F42: https://investors.etoro.com/news-releases (quarterly results; via search summaries) | G42: CO/AGG
A43: AUA_Q2_26 | B43: AUA Q2 2026 | C43: 19.2 | D43: $bn | E43: Q2_26 | F43: https://investors.etoro.com/news-releases (quarterly results; via search summaries) | G43: CO/AGG
A44: AUA_Aug26 | B44: AUA August 2026 | C44: 20.2 | D44: $bn | E44: Aug-26 | F44: https://www.manilatimes.net/2026/09/14/tmt-newswire/globenewswire/etoro-reports-selected-august-business-metrics/2424521 | G44: CO | H44: +3% YoY
A45: FA_Aug26 | B45: Funded accounts August 2026 | C45: 4.28 | D45: m | E45: Aug-26 | F45: same | G45: CO | H45: Identical to 30 Jun figure: possible stale repeat
A46: eToro: annual (US$m)
A47: NC_2023 | B47: Net contribution 2023 (LOW CONFIDENCE: 'revenue (total fees)') | C47: 639 | D47: $m | E47: FY23 | F47: https://www.calcalistech.com/ctechnews/article/sj6ykcjakg | G47: PR
A48: NC_2024 | B48: Net contribution 2024 | C48: 788 | D48: $m | E48: FY24 | F48: https://www.nasdaq.com/press-release/etoro-reports-fourth-quarter-and-full-year-2025-results-2026-02-17 | G48: CO
A49: NC_2025 | B49: Net contribution 2025 | C49: 868 | D49: $m | E49: FY25 | F49: https://www.financemagnates.com/fintech/etoro-reports-868m-net-contribution-for-2025-funded-accounts-rise-to-38-million/ | G49: CO
A50: EB_2023 | B50: Adj. EBITDA 2023 | C50: 117 | D50: $m | E50: FY23 | F50: https://www.calcalistech.com/ctechnews/article/sj6ykcjakg | G50: PR
A51: EB_2024 | B51: Adj. EBITDA 2024 | C51: 304 | D51: $m | E51: FY24 | F51: https://www.nasdaq.com/press-release/etoro-reports-fourth-quarter-and-full-year-2025-results-2026-02-17 | G51: CO
A52: EB_2025 | B52: Adj. EBITDA 2025 | C52: 317 | D52: $m | E52: FY25 | F52: https://www.nasdaq.com/press-release/etoro-reports-fourth-quarter-and-full-year-2025-results-2026-02-17 | G52: CO
A53: NI_2023 | B53: GAAP net income 2023 | C53: 15.3 | D53: $m | E53: FY23 | F53: https://www.calcalistech.com/ctechnews/article/sj6ykcjakg | G53: PR
A54: NI_2024 | B54: GAAP net income 2024 | C54: 192 | D54: $m | E54: FY24 | F54: https://www.nasdaq.com/press-release/etoro-reports-fourth-quarter-and-full-year-2025-results-2026-02-17 | G54: CO
A55: NI_2025 | B55: GAAP net income 2025 | C55: 216 | D55: $m | E55: FY25 | F55: https://www.nasdaq.com/press-release/etoro-reports-fourth-quarter-and-full-year-2025-results-2026-02-17 | G55: CO
A56: eToro: stated growth rates and headline claims (for cross-check)
A57: S_NC_FY25 | B57: Stated NC growth FY25 | C57: 0.1 | D57: % | F57: https://www.nasdaq.com/press-release/etoro-reports-fourth-quarter-and-full-year-2025-results-2026-02-17 | G57: CO
A58: S_NI_FY25 | B58: Stated NI growth FY25 | C58: 0.12 | D58: % | F58: https://www.nasdaq.com/press-release/etoro-reports-fourth-quarter-and-full-year-2025-results-2026-02-17 | G58: CO
A59: S_EB_FY25 | B59: Stated adj EBITDA growth FY25 | C59: 0.04 | D59: % | F59: https://www.nasdaq.com/press-release/etoro-reports-fourth-quarter-and-full-year-2025-results-2026-02-17 | G59: CO
A60: S_NC_Q2_26 | B60: Stated NC growth Q2 26 | C60: 0.09 | D60: % | F60: https://investors.etoro.com/news-releases/news-release-details/etoro-reports-second-quarter-2026-results | G60: CO
A61: S_EB_Q2_26 | B61: Stated adj EBITDA growth Q2 26 | C61: 0.09 | D61: % | F61: https://investors.etoro.com/news-releases/news-release-details/etoro-reports-second-quarter-2026-results | G61: CO
A62: S_NI_Q2_26 | B62: Stated NI growth Q2 26 | C62: 0.77 | D62: % | F62: https://investors.etoro.com/news-releases/news-release-details/etoro-reports-second-quarter-2026-results | G62: CO
A63: S_NC_Q1_26 | B63: Stated NC growth Q1 26 | C63: 0.19 | D63: % | F63: https://www.etoro.com/en-us/news-and-analysis/latest-news/press-release/etoro-reports-q1-2026-results/ | G63: CO
A64: S_NI_Q1_26 | B64: Stated NI growth Q1 26 | C64: 0.37 | D64: % | F64: https://www.etoro.com/en-us/news-and-analysis/latest-news/press-release/etoro-reports-q1-2026-results/ | G64: CO
A65: S_EB_Q1_26 | B65: Stated adj EBITDA growth Q1 26 | C65: 0.35 | D65: % | F65: https://www.etoro.com/en-us/news-and-analysis/latest-news/press-release/etoro-reports-q1-2026-results/ | G65: CO
A66: S_NC_Q3_25 | B66: Stated NC growth Q3 25 | C66: 0.28 | D66: % | F66: https://www.nasdaq.com/press-release/etoro-reports-third-quarter-2025-results-2025-11-10 | G66: CO
A67: S_EB_Q3_25 | B67: Stated adj EBITDA growth Q3 25 | C67: 0.43 | D67: % | F67: https://www.nasdaq.com/press-release/etoro-reports-third-quarter-2025-results-2025-11-10 | G67: CO
A68: S_NI_Q3_25 | B68: Stated NI growth Q3 25 | C68: 0.48 | D68: % | F68: https://www.nasdaq.com/press-release/etoro-reports-third-quarter-2025-results-2025-11-10 | G68: CO
... A76: S_REV_Q2_26_FXNG | B76: Press 'revenue' growth Q2 26 (FX News Group) | C76: -0.11 | D76: % | F76: https://fxnewsgroup.com/forex-news/retail-forex/etoro-shares-drop-10-as-revenues-fall-11-in-q2-2026-to-229-million/ | G76: CO
A77: TOTREV_Q2_26 | B77: Total revenues & income Q2 26 | C77: 1593 | D77: $m | E77: Q2 26 | F77: https://www.coindesk.com/business/2026/08/11/digital-broker-etoro-reports-q2-crypto-revenue-dropped-120-compared-to-2025 | G77: PR
A78: TOTREV_Q2_25 | B78: Total revenues & income Q2 25 | C78: 2094 | D78: $m | E78: Q2 25 | F78: same | G78: PR
A79: CRYPTO_Q2_26 | B79: Crypto gross revenue Q2 26 | C79: 1350 | D79: $m | E79: Q2 26 | F79: same | G79: PR
A80: CRYPTO_Q2_25 | B80: Crypto gross revenue Q2 25 | C80: 1910 | D80: $m | E80: Q2 25 | F80: same | G80: PR | H80: Press headline claims crypto revenue 'dropped 120%'
A81: NC_CM_Q2_26 | B81: NC: capital markets Q2 26 | C81: 142 | D81: $m | E81: Q2 26 | F81: https://www.investing.com/news/company-news/etoro-q2-2026-slides-ai-push-tradezero-deal-amid-crypto-retreat-93CH-4851953 | G81: PR
A82: NC_CR_Q2_26 | B82: NC: crypto Q2 26 | C82: 11 | D82: $m | E82: Q2 26 | F82: same | G82: PR
A83: NC_NII_Q2_26 | B83: NC: net interest income Q2 26 | C83: 49 | D83: $m | E83: Q2 26 | F83: same | G83: PR
A84: NC_MON_Q2_26 | B84: NC: eToro Money Q2 26 | C84: 26 | D84: $m | E84: Q2 26 | F84: same | G84: PR
A85: CRYPTO_SHARE_Q4_24 | B85: Crypto share of trading commission Q4 24 | C85: 0.5 | D85: % | E85: Q4 24 | F85: same | G85: PR
A86: CRYPTO_SHARE_Q2_26 | B86: Crypto share of trading commission Q2 26 | C86: 0.11 | D86: % | E86: Q2 26 | F86: same | G86: PR
A87: eToro: capital, valuation and corporate
A88: PX_ETOR | B88: ETOR share price | C88: 26.4 | D88: $ | E88: 28-Sep-26 | F88: https://www.investing.com/equities/etoro-group-ltd | G88: AGG
A89: SH_AGG | B89: Shares outstanding (latest aggregator, base case) | C89: 79.53 | D89: m | E89: Sep-26 | F89: https://stockanalysis.com/stocks/etor/statistics/ | G89: AGG
A90: SH_20F | B90: Shares outstanding 20-F (68.65m Cl A + 14.20m Cl B) | C90: 82.85 | D90: m | E90: 31-Dec-25 | F90: https://www.sec.gov/Archives/edgar/data/0001493318/000121390026022034/ea0278371-20f_etoro.htm | G90: CO
A91: SH_COVER | B91: Shares per Feb-26 6-K cover (rejected: does not reconcile to 20-F Cl B) | C91: 70.04 | D91: m | E91: 20-Feb-26 | F91: https://www.sec.gov/Archives/edgar/data/1493318/000121390026018169/ea0277653-6k_etoro.htm | G91: CO
A92: EPS_DIL_Q2_26 | B92: Diluted EPS Q2 26 | C92: 0.58 | D92: $ | E92: Q2 26 | F92: https://www.quiverquant.com/news/ETORO+GROUP+($ETOR)+Releases+Q2+2026+Earnings | G92: AGG
A93: CASH_ETOR | B93: Cash, cash equivalents & ST investments | C93: 1200 | D93: $m | E93: 30-Jun-26 | F93: https://investors.etoro.com/news-releases/news-release-details/etoro-reports-second-quarter-2026-results | G93: CO | H93: Split corporate vs regulatory capital N/D
A94: DEBT_ETOR | B94: Financial debt (assumed nil; N/D) | C94: 0 | D94: $m | E94: 30-Jun-26 | F94: N/D | G94: - | H94: Assumption
A95: IPO_PX | B95: IPO price | C95: 52 | D95: $ | E95: 13-May-25 | F95: https://www.cnbc.com/2025/05/13/etoro-prices-ipo-52-per-share.html | G95: PR
A96: IPO_VAL | B96: IPO valuation | C96: 4200 | D96: $m | E96: 13-May-25 | F96: same | G96: PR
A97: IPO_PRIMARY | B97: IPO primary proceeds to company (5.96m sh x $52) | C97: 310 | D97: $m | E97: May-25 | F97: https://www.investmentnews.com/ria-news/robinhood-rival-etoro-raises-almost-620m-in-us-ipo/260506 | G97: PR
A98: RAISE_2023 | B98: 2023 funding round (via 2021 AIA) at $3.5bn | C98: 250 | D98: $m | E98: Mar-23 | F98: https://techcrunch.com/2023/03/21/after-calling-off-spac-fintech-etoro-secures-250m-at-a-3-5b-valuation/ | G98: PR
A99: SPAC_VAL | B99: SPAC valuation (terminated Jul 2022) | C99: 10400 | D99: $m | E99: Mar-21 | F99: https://www.coindesk.com/business/2022/07/05/etoro-spac-deal-for-public-listing-canceled-as-transaction-becomes-impracticable | G99: PR
A100: BUYBACK_ASR | B100: Accelerated share repurchase (Citi) | C100: 50 | D100: $m | E100: Feb-26 | F100: https://www.theglobeandmail.com/investing/markets/stocks/ETOR/pressreleases/329879/ | G100: CO
A101: INSIDER_VOTE | B101: Yoni Assia voting power post-IPO | C101: 0.0934 | D101: % | E101: May-25 | F101: https://www.calcalistech.com/ctechnews/article/h1pgtdleel | G101: PR
A102: TZ_PRICE | B102: TradeZero max consideration | C102: 231 | D102: $m | E102: Aug-26 | F102: https://finance.yahoo.com/markets/stocks/articles/etoro-strikes-231m-tradezero-deal-171400979.html | G102: CO
A103: TZ_REV | B103: TradeZero LTM revenue | C103: 80 | D103: $m | E103: LTM Q2 26 | F103: same | G103: CO
A104: TZ_SH | B104: TradeZero max new eToro shares | C104: 2.5 | D104: m | E104: Aug-26 | F104: same | G104: CO
A105: TZ_STATED | B105: TradeZero stated EV/revenue | C105: 2.9 | D105: x | F105: same | G105: PR
A106: SPACESHIP_CLIENTS | B106: Spaceship clients acquired (upper bound) | C106: 0.2 | D106: m | E106: 2024-25 | F106: https://investors.etoro.com/news-releases/news-release-details/etoro-expands-long-term-savings-offer-acquisition-spaceship-deal | G106: CO
A107: INITIATIVES | B107: Concurrent forward initiatives (count; see list in Scorecard) | C107: 8 | D107: # | E107: Sep-26 | F107: Analyst count from company releases | G107: Analyst
A108: REVERSED | B108: Reversed or abandoned strategic decisions (SPAC 2021-22) | C108: 1 | D108: # | F108: coindesk (above) | G108: PR
A109: FX (mid-market, late Sep 2026)
A110: FX_GBP | B110: USD per GBP | C110: 1.3245 | E110: 25-Sep-26 | F110: https://www.mtfxgroup.com/tools/historical-currency-exchange-rates/gbp-to-usd-rate/ | G110: AGG
A111: FX_EUR | B111: USD per EUR | C111: 1.146 | E111: 18-Sep-26 | F111: same | G111: AGG
A112: FX_CHF_INV | B112: CHF per USD | C112: 0.82819 | E112: Sep-26 | F112: same | G112: AGG
A113: FX_PLN | B113: USD per PLN | C113: 0.26946 | E113: Sep-26 | F113: same | G113: AGG
A114: Peers (local currency, millions unless stated)
A115: IG_REV_CY25 | B115: IG total revenue CY25 | C115: 1123.4 | D115: GBPm | E115: CY25 | F115: https://www.financemagnates.com/forex/brokers/ig-group-posts-record-112bn-revenue-launches-strategic-review-as-customer-growth-accelerates/amp/ | G115: CO
A116: IG_REV_H126 | B116: IG total revenue H1 26 | C116: 642.8 | D116: GBPm | E116: H1 26 | F116: https://www.investing.com/news/company-news/ig-group-h1-2026-slides-strong-growth-offset-by-margin-pressure-93CH-4827248 | G116: CO
A117: IG_REV_H1G | B117: IG H1 26 revenue growth | C117: 0.18 | D117: % | E117: H1 26 | F117: https://www.investing.com/news/company-news/ig-group-h1-2026-slides-strong-growth-offset-by-margin-pressure-93CH-4827248 | G117: CO
A118: IG_EBITDA_CY25 | B118: IG EBITDA CY25 | C118: 531.1 | D118: GBPm | E118: CY25 | F118: https://www.financemagnates.com/forex/brokers/ig-group-posts-record-112bn-revenue-launches-strategic-review-as-customer-growth-accelerates/amp/ | G118: CO
...

Sheet Historical Build & Ratios
A1: Historical build & ratios: eToro (US$m). All formulas; green = link to Inputs. Derived quarters are marked.
A3: Quarterly | B3: Q1 24 | C3: Q2 24 | D3: Q3 24 | E3: Q4 24 | F3: Q1 25 | G3: Q2 25 | H3: Q3 25 | I3: Q4 25 | J3: Q1 26 | K3: Q2 26 | M3: Note
A4: Net contribution ($m) | B4: =Inputs!$C$5 -> 201 | C4: =Inputs!$C$48-Inputs!$C$5-Inputs!$C$6-Inputs!$C$7 -> 167 | D4: =Inputs!$C$6 -> 167 | E4: =Inputs!$C$7 -> 253 | F4: =Inputs!$C$8 -> 217 | G4: =Inputs!$C$9 -> 210 | H4: =Inputs!$C$10 -> 215 | I4: =Inputs!$C$11 -> 227 | J4: =Inputs!$C$12 -> 258 | K4: =Inputs!$C$13 -> 229 | M4: Q2 24 derived = FY24 less Q1, Q3, Q4
A5: Adj. EBITDA ($m) | B5: =Inputs!$C$14 -> 87 | C5: =Inputs!$C$15 -> 55 | D5: =Inputs!$C$16 -> 55 | E5: =Inputs!$C$17 -> 108 | F5: =Inputs!$C$18 -> 80 | G5: =Inputs!$C$19 -> 72 | H5: =Inputs!$C$20 -> 78 | I5: =Inputs!$C$52-Inputs!$C$18-Inputs!$C$19-Inputs!$C$20 -> 87 | J5: =Inputs!$C$21 -> 109 | K5: =Inputs!$C$22 -> 78 | M5: Q4 25 derived = FY25 less Q1-Q3
A6: GAAP net income ($m) | B6: =Inputs!$C$23 -> 64 | C6: =Inputs!$C$24 -> 30.6 | D6: =Inputs!$C$25 -> 39 | E6: =Inputs!$C$26 -> 59 | F6: =Inputs!$C$27 -> 60 | G6: =Inputs!$C$28 -> 30.2 | H6: =Inputs!$C$29 -> 57 | I6: =Inputs!$C$55-Inputs!$C$27-Inputs!$C$28-Inputs!$C$29 -> 68.8 | J6: =Inputs!$C$30 -> 82 | K6: =Inputs!$C$31 -> 53 | M6: Q4 25 derived = FY25 less Q1-Q3
A7: Funded accounts (m) | D7: =Inputs!$C$32 -> 3.21 | F7: =Inputs!$C$33 -> 3.58 | G7: =Inputs!$C$34 -> 3.63 | H7: =Inputs!$C$35 -> 3.73 | I7: =Inputs!$C$36 -> 3.85 | J7: =Inputs!$C$37 -> 4.02 | K7: =Inputs!$C$38 -> 4.28 | M7: Blank = N/D
A8: AUA ($bn) | G8: =Inputs!$C$39 -> 17.5 | H8: =Inputs!$C$40 -> 20.8 | I8: =Inputs!$C$41 -> 18.5 | J8: =Inputs!$C$42 -> 18.7 | K8: =Inputs!$C$43 -> 19.2 | M8: Blank = N/D; Q3 25 via aggregator
A10: NC YoY growth | F10: =F4/B4-1 -> 0.07960199 | G10: =G4/C4-1 -> 0.25748503 | H10: =H4/D4-1 -> 0.28742515 | I10: =I4/E4-1 -> -0.1027668 | J10: =J4/F4-1 -> 0.18894009 | K10: =K4/G4-1 -> 0.09047619
A11: Adj. EBITDA YoY growth | F11: =F5/B5-1 -> -0.08045977 | G11: =G5/C5-1 -> 0.30909091 | H11: =H5/D5-1 -> 0.41818182 | I11: =I5/E5-1 -> -0.19444444 | J11: =J5/F5-1 -> 0.3625 | K11: =K5/G5-1 -> 0.083333333
A12: Net income YoY growth | F12: =F6/B6-1 -> -0.0625 | G12: =G6/C6-1 -> -0.013071895 | H12: =H6/D6-1 -> 0.46153846 | I12: =I6/E6-1 -> 0.16610169 | J12: =J6/F6-1 -> 0.36666667 | K12: =K6/G6-1 -> 0.75496689
A13: Adj. EBITDA margin (on NC) | B13: =B5/B4 -> 0.43283582 | C13: =C5/C4 -> 0.32934132 | D13: =D5/D4 -> 0.32934132 | E13: =E5/E4 -> 0.42687747 | F13: =F5/F4 -> 0.36866359 | G13: =G5/G4 -> 0.34285714 | H13: =H5/H4 -> 0.3627907 | I13: =I5/I4 -> 0.38325991 | ... K13: =K5/K4 -> 0.34061135
A14: Net margin (NI / NC) | B14: =B6/B4 -> 0.31840796 | C14: =C6/C4 -> 0.18323353 | D14: =D6/D4 -> 0.23353293 | E14: =E6/E4 -> 0.23320158 | F14: =F6/F4 -> 0.2764977 | G14: =G6/G4 -> 0.14380952 | H14: =H6/H4 -> 0.26511628 | I14: =I6/I4 -> 0.3030837 | ... K14: =K6/K4 -> 0.23144105
A15: Profitable quarter (1 = NI > 0) | B15: =IF(B6>0,1,0) -> 1 | C15: =IF(C6>0,1,0) -> 1 | D15: =IF(D6>0,1,0) -> 1 | E15: =IF(E6>0,1,0) -> 1 | F15: =IF(F6>0,1,0) -> 1 | G15: =IF(G6>0,1,0) -> 1 | H15: =IF(H6>0,1,0) -> 1 | I15: =IF(I6>0,1,0) -> 1 | ... K15: =IF(K6>0,1,0) -> 1
A16: Take-rate: annualised NC / AUA | B16: =IF(ISNUMBER(B8),B4*4/(B8*1000),"N/D") -> N/D | C16: =IF(ISNUMBER(C8),C4*4/(C8*1000),"N/D") -> N/D | D16: =IF(ISNUMBER(D8),D4*4/(D8*1000),"N/D") -> N/D | E16: =IF(ISNUMBER(E8),E4*4/(E8*1000),"N/D") -> N/D | F16: =IF(ISNUMBER(F8),F4*4/(F8*1000),"N/D") -> N/D | G16: =IF(ISNUMBER(G8),G4*4/(G8*1000),"N/D") -> 0.048 | H16: =IF(ISNUMBER(H8),H4*4/(H8*1000),"N/D") -> 0.041346154 | I16: =IF(ISNUMBER(I8),I4*4/(I8*1000),"N/D") -> 0.049081081 | ... K16: =IF(ISNUMBER(K8),K4*4/(K8*1000),"N/D") -> 0.047708333 | M16: Uses period-end AUA (not average)
A17: Annualised NC per funded account ($) | B17: =IF(ISNUMBER(B7),B4*4/B7,"N/D") -> N/D | C17: =IF(ISNUMBER(C7),C4*4/C7,"N/D") -> N/D | D17: =IF(ISNUMBER(D7),D4*4/D7,"N/D") -> 208.09969 | E17: =IF(ISNUMBER(E7),E4*4/E7,"N/D") -> N/D | F17: =IF(ISNUMBER(F7),F4*4/F7,"N/D") -> 242.4581 | G17: =IF(ISNUMBER(G7),G4*4/G7,"N/D") -> 231.40496 | H17: =IF(ISNUMBER(H7),H4*4/H7,"N/D") -> 230.563 | I17: =IF(ISNUMBER(I7),I4*4/I7,"N/D") -> 235.84416 | ... K17: =IF(ISNUMBER(K7),K4*4/K7,"N/D") -> 214.01869
A18: Funded accounts YoY growth | F18: =IF(AND(ISNUMBER(F7),ISNUMBER(B7)),F7/B7-1,"N/D") -> N/D | G18: =IF(AND(ISNUMBER(G7),ISNUMBER(C7)),G7/C7-1,"N/D") -> N/D | H18: =IF(AND(ISNUMBER(H7),ISNUMBER(D7)),H7/D7-1,"N/D") -> 0.16199377 | I18: =IF(AND(ISNUMBER(I7),ISNUMBER(E7)),I7/E7-1,"N/D") -> N/D | J18: =IF(AND(ISNUMBER(J7),ISNUMBER(F7)),J7/F7-1,"N/D") -> 0.12290503 | K18: =IF(AND(ISNUMBER(K7),ISNUMBER(G7)),K7/G7-1,"N/D") -> 0.17906336
A21: Annual / LTM | B21: FY23 | C21: FY24 | D21: FY25 | E21: LTM Q2 26 | F21: Prior LTM Q2 25 | G21: H1 25 | H21: H1 26 | M21: Note
A22: Net contribution ($m) | B22: =Inputs!$C$47 -> 639 | C22: =Inputs!$C$48 -> 788 | D22: =Inputs!$C$49 -> 868 | E22: =SUM(H4:K4) -> 929 | F22: =SUM(D4:G4) -> 847 | G22: =SUM(F4:G4) -> 427 | H22: =SUM(J4:K4) -> 487
A23: Adj. EBITDA ($m) | B23: =Inputs!$C$50 -> 117 | C23: =Inputs!$C$51 -> 304 | D23: =Inputs!$C$52 -> 317 | E23: =SUM(H5:K5) -> 352 | F23: =SUM(D5:G5) -> 315 | G23: =SUM(F5:G5) -> 152 | H23: =SUM(J5:K5) -> 187
A24: GAAP net income ($m) | B24: =Inputs!$C$53 -> 15.3 | C24: =Inputs!$C$54 -> 192 | D24: =Inputs!$C$55 -> 216 | E24: =SUM(H6:K6) -> 260.8 | F24: =SUM(D6:G6) -> 188.2 | G24: =SUM(F6:G6) -> 90.2 | H24: =SUM(J6:K6) -> 135
A25: YoY growth | C25: =C22/B22-1 -> 0.23317684 | D25: =D22/C22-1 -> 0.10152284 | E25: =E22/F22-1 -> 0.096812279 | H25: =H22/G22-1 -> 0.14051522
A26: Adj. EBITDA margin | B26: =B23/B22 -> 0.18309859 | C26: =C23/C22 -> 0.3857868 | D26: =D23/D22 -> 0.36520737 | E26: =E23/E22 -> 0.37890205 | F26: =F23/F22 -> 0.37190083 | G26: =G23/G22 -> 0.3559719 | H26: =H23/H22 -> 0.38398357
A27: Net margin | B27: =B24/B22 -> 0.023943662 | C27: =C24/C22 -> 0.24365482 | D27: =D24/D22 -> 0.24884793 | E27: =E24/E22 -> 0.28073197 | F27: =F24/F22 -> 0.22219599 | G27: =G24/G22 -> 0.21124122 | H27: =H24/H22 -> 0.27720739
A28: NC CAGR FY23-FY25 | B28: =(D22/B22)^(1/2)-1 -> 0.16549237
A29: Adj. EBITDA CAGR FY23-FY25 | B29: =(D23/B23)^(1/2)-1 -> 0.64602604
A30: NC CAGR FY24-LTM (1.5 yrs) | B30: =(E22/C22)^(1/1.5)-1 -> 0.11598836
A31: LTM NI growth | B31: =E24/F24-1 -> 0.38575983
A32: LTM adj. EBITDA growth | B32: =E23/F23-1 -> 0.11746032
A33: STDEVP adj. EBITDA margin, 10 qtrs | B33: =STDEVP(B13:K13) -> 0.038628111
A34: STDEVP adj. EBITDA margin, last 5 qtrs | B34: =STDEVP(G13:K13) -> 0.030270918
A35: Profitable quarters / disclosed quarters | B35: =SUM(B15:K15) -> 10 | C35: =COUNT(B6:K6) -> 10 | D35: =B35/C35 -> 1
A36: Cumulative GAAP NI FY23 to H1 26 ($m) | B36: =B24+C24+D24+H24 -> 558.3
A37: Total revenues & income growth Q2 26 | B37: =Inputs!$C$77/Inputs!$C$78-1 -> -0.23925501
A38: Crypto gross revenue growth Q2 26 | B38: =Inputs!$C$79/Inputs!$C$80-1 -> -0.29319372
A39: Sum of Q2 26 NC components ($m) | B39: =Inputs!$C$81+Inputs!$C$82+Inputs!$C$83+Inputs!$C$84 -> 228
A40: Capital-markets share of Q2 26 NC | B40: =Inputs!$C$81/K4 -> 0.62008734
A41: Net interest income share of Q2 26 NC | B41: =Inputs!$C$83/K4 -> 0.2139738
A45: Cross-check (recomputed vs stated) | B45: Recomputed | C45: Stated | D45: Diff | E45: Tolerance | F45: Result | M45: Tolerance 2pp on growth/margins because inputs are rounded to $1m in the summaries
A46: NC growth FY25 | B46: =D25 -> 0.10152284 | C46: =Inputs!$C$57 -> 0.1 | D46: =B46-C46 -> 0.0015228426 | E46: =Inputs!$C$190 -> 0.02 | F46: =IF(ABS(D46)<=E46,"MATCH","FLAG") -> MATCH
A47: NI growth FY25 | B47: =D24/C24-1 -> 0.125 | C47: =Inputs!$C$58 -> 0.12 | D47: =B47-C47 -> 0.005 | E47: =Inputs!$C$190 -> 0.02 | F47: =IF(ABS(D47)<=E47,"MATCH","FLAG") -> MATCH
A48: Adj. EBITDA growth FY25 | B48: =D23/C23-1 -> 0.042763158 | C48: =Inputs!$C$59 -> 0.04 | D48: =B48-C48 -> 0.0027631579 | E48: =Inputs!$C$190 -> 0.02 | F48: =IF(ABS(D48)<=E48,"MATCH","FLAG") -> MATCH
A49: NC growth Q2 26 | B49: =K10 -> 0.09047619 | C49: =Inputs!$C$60 -> 0.09 | D49: =B49-C49 -> 0.00047619048 | E49: =Inputs!$C$190 -> 0.02 | F49: =IF(ABS(D49)<=E49,"MATCH","FLAG") -> MATCH
A50: Adj. EBITDA growth Q2 26 | B50: =K11 -> 0.083333333 | C50: =Inputs!$C$61 -> 0.09 | D50: =B50-C50 -> -0.0066666667 | E50: =Inputs!$C$190 -> 0.02 | F50: =IF(ABS(D50)<=E50,"MATCH","FLAG") -> MATCH
A51: NI growth Q2 26 | B51: =K12 -> 0.75496689 | C51: =Inputs!$C$62 -> 0.77 | D51: =B51-C51 -> -0.015033113 | E51: =Inputs!$C$190 -> 0.02 | F51: =IF(ABS(D51)<=E51,"MATCH","FLAG") -> MATCH
A52: NC growth Q1 26 | B52: =J10 -> 0.18894009 | C52: =Inputs!$C$63 -> 0.19 | D52: =B52-C52 -> -0.0010599078 | E52: =Inputs!$C$190 -> 0.02 | F52: =IF(ABS(D52)<=E52,"MATCH","FLAG") -> MATCH
A53: NI growth Q1 26 | B53: =J12 -> 0.36666667 | C53: =Inputs!$C$64 -> 0.37 | D53: =B53-C53 -> -0.0033333333 | E53: =Inputs!$C$190 -> 0.02 | F53: =IF(ABS(D53)<=E53,"MATCH","FLAG") -> MATCH
A54: Adj. EBITDA growth Q1 26 | B54: =J11 -> 0.3625 | C54: =Inputs!$C$65 -> 0.35 | D54: =B54-C54 -> 0.0125 | E54: =Inputs!$C$190 -> 0.02 | F54: =IF(ABS(D54)<=E54,"MATCH","FLAG") -> MATCH
A55: NC growth Q3 25 | B55: =H10 -> 0.28742515 | C55: =Inputs!$C$66 -> 0.28 | D55: =B55-C55 -> 0.0074251497 | E55: =Inputs!$C$190 -> 0.02 | F55: =IF(ABS(D55)<=E55,"MATCH","FLAG") -> MATCH
A56: Adj. EBITDA growth Q3 25 | B56: =H11 -> 0.41818182 | C56: =Inputs!$C$67 -> 0.43 | D56: =B56-C56 -> -0.011818182 | E56: =Inputs!$C$190 -> 0.02 | F56: =IF(ABS(D56)<=E56,"MATCH","FLAG") -> MATCH
A57: NI growth Q3 25 | B57: =H12 -> 0.46153846 | C57: =Inputs!$C$68 -> 0.48 | D57: =B57-C57 -> -0.018461538 | E57: =Inputs!$C$190 -> 0.02 | F57: =IF(ABS(D57)<=E57,"MATCH","FLAG") -> MATCH
A58: NC growth Q2 25 (on derived Q2 24) | B58: =G10 -> 0.25748503 | C58: =Inputs!$C$69 -> 0.26 | D58: =B58-C58 -> -0.0025149701 | E58: =Inputs!$C$190 -> 0.02 | F58: =IF(ABS(D58)<=E58,"MATCH","FLAG") -> MATCH
A59: Adj. EBITDA growth Q2 25 | B59: =G11 -> 0.30909091 | C59: =Inputs!$C$70 -> 0.31 | D59: =B59-C59 -> -0.00090909091 | E59: =Inputs!$C$190 -> 0.02 | F59: =IF(ABS(D59)<=E59,"MATCH","FLAG") -> MATCH
A60: NC growth Q1 25 | B60: =F10 -> 0.07960199 | C60: =Inputs!$C$71 -> 0.08 | D60: =B60-C60 -> -0.00039800995 | E60: =Inputs!$C$190 -> 0.02 | F60: =IF(ABS(D60)<=E60,"MATCH","FLAG") -> MATCH
A61: Funded-account growth Q2 26 | B61: =K18 -> 0.17906336 | C61: =Inputs!$C$72 -> 0.18 | D61: =B61-C61 -> -0.00093663912 | E61: =Inputs!$C$190 -> 0.02 | F61: =IF(ABS(D61)<=E61,"MATCH","FLAG") -> MATCH
A62: Funded-account growth Q3 25 | B62: =H18 -> 0.16199377 | C62: =Inputs!$C$74 -> 0.16 | D62: =B62-C62 -> 0.0019937695 | E62: =Inputs!$C$190 -> 0.02 | F62: =IF(ABS(D62)<=E62,"MATCH","FLAG") -> MATCH
A63: AUA growth Q2 26 (vs Q2 25) | B63: =K8/G8-1 -> 0.097142857 | C63: =Inputs!$C$73 -> 0.1 | D63: =B63-C63 -> -0.0028571429 | E63: =Inputs!$C$190 -> 0.02 | F63: =IF(ABS(D63)<=E63,"MATCH","FLAG") -> MATCH
A64: Adj. EBITDA margin Q2 26 | B64: =K13 -> 0.34061135 | C64: =Inputs!$C$75 -> 0.34 | D64: =B64-C64 -> 0.00061135371 | E64: =Inputs!$C$190 -> 0.02 | F64: =IF(ABS(D64)<=E64,"MATCH","FLAG") -> MATCH
A65: Press 'revenue' growth Q2 26 vs NC growth | B65: =K10 -> 0.09047619 | C65: =Inputs!$C$76 -> -0.11 | D65: =B65-C65 -> 0.20047619 | E65: =Inputs!$C$190 -> 0.02 | F65: =IF(ABS(D65)<=E65,"MATCH","FLAG") -> FLAG
A66: Press 'revenue' growth Q2 26 vs total revenues & income | B66: =B37 -> -0.23925501 | C66: =Inputs!$C$76 -> -0.11 | D66: =B66-C66 -> -0.12925501 | E66: =Inputs!$C$190 -> 0.02 | F66: =IF(ABS(D66)<=E66,"MATCH","FLAG") -> FLAG
A67: Sum of FY25 quarters vs FY25 NC ($m) | B67: =SUM(F4:I4) -> 869 | C67: =Inputs!$C$49 -> 868 | D67: =B67-C67 -> 1 | E67: =Inputs!$C$191 -> 2 | F67: =IF(ABS(D67)<=E67,"MATCH","FLAG") -> MATCH
A68: Sum of FY24 EBITDA quarters vs FY24 ($m) | B68: =SUM(B5:E5) -> 305 | C68: =Inputs!$C$51 -> 304 | D68: =B68-C68 -> 1 | E68: =Inputs!$C$191 -> 2 | F68: =IF(ABS(D68)<=E68,"MATCH","FLAG") -> MATCH
A69: Sum of FY24 NI quarters vs FY24 ($m) | B69: =SUM(B6:E6) -> 192.6 | C69: =Inputs!$C$54 -> 192 | D69: =B69-C69 -> 0.6 | E69: =Inputs!$C$191 -> 2 | F69: =IF(ABS(D69)<=E69,"MATCH","FLAG") -> MATCH
A70: Q2 26 NC components vs reported NC ($m) | B70: =B39 -> 228 | C70: =K4 -> 229 | D70: =B70-C70 -> -1 | E70: =Inputs!$C$191 -> 2 | F70: =IF(ABS(D70)<=E70,"MATCH","FLAG") -> MATCH
A71: Q4 25 derived NC (FY less Q1-Q3) vs stated Q4 NC ($m) | B71: =Inputs!$C$49-F4-G4-H4 -> 226 | C71: =I4 -> 227 | D71: =B71-C71 -> -1 | E71: =Inputs!$C$191 -> 2 | F71: =IF(ABS(D71)<=E71,"MATCH","FLAG") -> MATCH
A72: Q4 25 funded accounts: release (3.85m) vs FY press (3.81m), m | B72: =I7 -> 3.85 | C72: =Inputs!$C$195 -> 3.81 | D72: =B72-C72 -> 0.04 | E72: =Inputs!$C$193 -> 0.005 | F72: =IF(ABS(D72)<=E72,"MATCH","FLAG") -> FLAG
A73: TradeZero EV/revenue | B73: =Inputs!$C$102/Inputs!$C$103 -> 2.8875 | C73: =Inputs!$C$105 -> 2.9 | D73: =B73-C73 -> -0.0125 | E73: =Inputs!$C$194 -> 0.1 | F73: =IF(ABS(D73)<=E73,"MATCH","FLAG") -> MATCH
A74: Freetrade price / trailing revenue vs '~5x run-rate' | B74: =Inputs!$C$174/Inputs!$C$175 -> 5.8181818 | C74: =Inputs!$C$178 -> 5 | D74: =B74-C74 -> 0.81818182 | E74: =Inputs!$C$194 -> 0.1 | F74: =IF(ABS(D74)<=E74,"MATCH","FLAG") -> FLAG
A75: Swissquote PBT margin H1 26 vs stated 50.2% | B75: =Inputs!$C$167/Inputs!$C$164 -> 0.42174629 | C75: =Inputs!$C$172 -> 0.502 | D75: =B75-C75 -> -0.080253707 | E75: =Inputs!$C$190 -> 0.02 | F75: =IF(ABS(D75)<=E75,"MATCH","FLAG") -> FLAG
A76: Swissquote market cap: price x shares vs quoted CHF 5.54bn | B76: =Inputs!$C$168*Inputs!$C$169 -> 5542.5624 | C76: =Inputs!$C$196 -> 5540 | D76: =B76-C76 -> 2.5624 | E76: =Inputs!$C$192 -> 10 | F76: =IF(ABS(D76)<=E76,"MATCH","FLAG") -> MATCH
A77: eToro market cap: price x 79.53m vs quoted $2.10bn | B77: =Inputs!$C$88*Inputs!$C$89 -> 2099.592 | C77: =Inputs!$C$197 -> 2100 | D77: =B77-C77 -> -0.408 | E77: =Inputs!$C$192 -> 10 | F77: =IF(ABS(D77)<=E77,"MATCH","FLAG") -> MATCH
A78: eToro diluted shares implied (NI/EPS) vs base 79.53m | B78: =Inputs!$C$31/Inputs!$C$92 -> 91.37931 | C78: =Inputs!$C$89 -> 79.53 | D78: =B78-C78 -> 11.84931 | E78: =Inputs!$C$193 -> 0.005 | F78: =IF(ABS(D78)<=E78,"MATCH","FLAG") -> FLAG
A80: Count of FLAGs | B80: =COUNTIF(F46:F78,"FLAG") -> 6
A81: Count of MATCHes | B81: =COUNTIF(F46:F78,"MATCH") -> 27

Sheet Peer Benchmark
A1: Peer benchmark (US$m unless stated). Revenue basis: eToro = net contribution; peers = total revenue / net revenue / operating income as labelled.
A3: Company | B3: Scale metric | C3: Scale (m) | D3: Client assets ($bn) | E3: Revenue basis | F3: Revenue ($m) | G3: Profit basis | H3: Profit ($m) | I3: Net income basis ($m) | J3: Market cap ($m) | K3: Corporate cash credited ($m) | L3: EV ($m) | M3: EV / Revenue (x) | N3: Mcap / Revenue (x) | O3: P/E (x) | P3: Revenue growth (latest) | Q3: EV/Rev per pt of growth | R3: Data quality
A4: eToro (base: 79.53m sh; 50% cash credit) | B4: Funded accounts | C4: ='Historical Build & Ratios'!K7 -> 4.28 | D4: ='Historical Build & Ratios'!K8 -> 19.2 | E4: LTM net contribution | F4: ='Historical Build & Ratios'!E22 -> 929 | G4: LTM adj. EBITDA | H4: ='Historical Build & Ratios'!E23 -> 352 | I4: ='Historical Build & Ratios'!E24 -> 260.8 | J4: =Inputs!$C$88*Inputs!$C$89 -> 2099.592 | K4: =Inputs!$C$93*Inputs!$C$188-Inputs!$C$94 -> 600 | L4: =IF(ISNUMBER(K4),J4-K4,J4) -> 1499.592 | M4: =IF(ISNUMBER(L4),L4/F4,"N/D") -> 1.6142002 | N4: =IF(ISNUMBER(J4),J4/F4,"N/D") -> 2.260056 | O4: =IF(AND(ISNUMBER(J4),ISNUMBER(I4)),J4/I4,"N/D") -> 8.0505828 | P4: ='Historical Build & Ratios'!H25 -> 0.14051522 | Q4: =IF(AND(ISNUMBER(M4),ISNUMBER(P4)),IF(P4>0,M4/(P4*100),"n.m."),"N/D") -> 0.11487725 | R4: Listed/audited (search-summary basis); Q2 26 funded acct = 30 Jun
A5: IG Group (CONFLICT: requester's employer) | B5: Active customers | C5: =Inputs!$C$123 -> 0.8436 | D5: =Inputs!$C$124*Inputs!$C$110 -> 28.47675 | E5: LTM total revenue | F5: =(Inputs!$C$116+Inputs!$C$115-Inputs!$C$116/(1+Inputs!$C$117))*Inputs!$C$110 -> 1617.8161 | G5: CY25 EBITDA | H5: =Inputs!$C$118*Inputs!$C$110 -> 703.44195 | I5: N/D | J5: =Inputs!$C$122*Inputs!$C$110 -> 5841.045 | K5: N/D | L5: =IF(ISNUMBER(K5),J5-K5,J5) -> 5841.045 | M5: =IF(ISNUMBER(L5),L5/F5,"N/D") -> 3.6104504 | N5: =IF(ISNUMBER(J5),J5/F5,"N/D") -> 3.6104504 | O5: =Inputs!$C$121/Inputs!$C$120 -> 11.603816 | P5: =Inputs!$C$117 -> 0.18 | Q5: =IF(AND(ISNUMBER(M5),ISNUMBER(P5)),IF(P5>0,M5/(P5*100),"n.m."),"N/D") -> 0.20058058 | R5: Listed/audited; H1 25 derived from stated growth; P/E on adj EPS
A6: Plus500 | B6: Active customers | C6: =Inputs!$C$134 -> 0.197 | D6: =Inputs!$C$135 -> 3.4 | E6: LTM revenue | F6: =Inputs!$C$126+Inputs!$C$125-Inputs!$C$126/(1+Inputs!$C$127) -> 841.60714 | G6: LTM EBITDA | H6: =Inputs!$C$129+Inputs!$C$128-Inputs!$C$129/(1+Inputs!$C$130) -> 349.85644 | I6: =Inputs!$C$131 -> 281.3 | J6: =Inputs!$C$132*Inputs!$C$110 -> 3337.74 | K6: =Inputs!$C$133 -> 800 | L6: =IF(ISNUMBER(K6),J6-K6,J6) -> 2537.74 | M6: =IF(ISNUMBER(L6),L6/F6,"N/D") -> 3.0153499 | N6: =IF(ISNUMBER(J6),J6/F6,"N/D") -> 3.9659122 | O6: =IF(AND(ISNUMBER(J6),ISNUMBER(I6)),J6/I6,"N/D") -> 11.865411 | P6: =Inputs!$C$127 -> 0.12 | Q6: =IF(AND(ISNUMBER(M6),ISNUMBER(P6)),IF(P6>0,M6/(P6*100),"n.m."),"N/D") -> 0.25127916 | R6: Listed/audited; NI = FY25; cash at YE25
A7: Webull | B7: Funded accounts | C7: =Inputs!$C$144 -> 5.13 | D7: =Inputs!$C$145 -> 28.5 | E7: LTM revenue | F7: =Inputs!$C$136-Inputs!$C$138-Inputs!$C$139/(1+Inputs!$C$140)+Inputs!$C$137+Inputs!$C$139 -> 680.64437 | G7: Q2 26 adj. op profit x4 | H7: =Inputs!$C$141*4 -> 250.4 | I7: N/D | J7: =Inputs!$C$143 -> 4380 | K7: N/D | L7: =IF(ISNUMBER(K7),J7-K7,J7) -> 4380 | M7: =IF(ISNUMBER(L7),L7/F7,"N/D") -> 6.4350786 | N7: =IF(ISNUMBER(J7),J7/F7,"N/D") -> 6.4350786 | O7: =IF(AND(ISNUMBER(J7),ISNUMBER(I7)),J7/I7,"N/D") -> N/D | P7: =(Inputs!$C$137+Inputs!$C$139)/(Inputs!$C$138+Inputs!$C$139/(1+Inputs!$C$140))-1 -> 0.44024048 | Q7: =IF(AND(ISNUMBER(M7),ISNUMBER(P7)),IF(P7>0,M7/(P7*100),"n.m."),"N/D") -> 0.14617189 | R7: Listed/audited; Q2 25 derived; LTM GAAP NI N/D
A8: XTB | B8: Active clients | C8: =Inputs!$C$154 -> 1.49 | D8: N/D | E8: LTM total operating income | F8: =(Inputs!$C$147+Inputs!$C$146-Inputs!$C$147/(1+Inputs!$C$148))*Inputs!$C$113 -> 828.67289 | G8: H1 26 EBITDA x2 | H8: =Inputs!$C$152*2*Inputs!$C$113 -> 655.32672 | I8: =(Inputs!$C$150+Inputs!$C$149-Inputs!$C$150/(1+Inputs!$C$151))*Inputs!$C$113 -> 339.77292 | J8: =Inputs!$C$153*Inputs!$C$113 -> 4947.2856 | K8: N/D | L8: =IF(ISNUMBER(K8),J8-K8,J8) -> 4947.2856 | M8: =IF(ISNUMBER(L8),L8/F8,"N/D") -> 5.9701309 | N8: =IF(ISNUMBER(J8),J8/F8,"N/D") -> 5.9701309 | O8: =IF(AND(ISNUMBER(J8),ISNUMBER(I8)),J8/I8,"N/D") -> 14.560565 | P8: =Inputs!$C$148 -> 0.797 | Q8: =IF(AND(ISNUMBER(M8),ISNUMBER(P8)),IF(P8>0,M8/(P8*100),"n.m."),"N/D") -> 0.074907539 | R8: Listed/audited; H1 25 derived; EBITDA annualised from one half
A9: Trading 212 (private) | B9: Funded accounts (group, self-rep.) | C9: =Inputs!$C$160 -> 4.5 | D9: =Inputs!$C$161*Inputs!$C$110 -> 43.033005 | E9: FY25 revenue (UK Ltd) | F9: =Inputs!$C$156*Inputs!$C$110 -> 367.6812 | G9: FY25 PBT (UK Ltd) | H9: =Inputs!$C$158*Inputs!$C$110 -> 163.04595 | I9: =Inputs!$C$159*Inputs!$C$110 -> 122.1189 | J9: N/D | K9: N/D | L9: N/D | M9: =IF(ISNUMBER(L9),L9/F9,"N/D") -> N/D | N9: =IF(ISNUMBER(J9),J9/F9,"N/D") -> N/D | O9: =IF(AND(ISNUMBER(J9),ISNUMBER(I9)),J9/I9,"N/D") -> N/D | P9: =Inputs!$C$156/Inputs!$C$157-1 -> 0.71675943 | Q9: =IF(AND(ISNUMBER(M9),ISNUMBER(P9)),IF(P9>0,M9/(P9*100),"n.m."),"N/D") -> N/D | R9: Private: UK entity audited (Companies House); group metrics self-reported; no valuation marker
A10: Swissquote | B10: Accounts | C10: =Inputs!$C$170 -> 1.2 | D10: =Inputs!$C$171/Inputs!$C$112 -> 116.27767 | E10: LTM net revenues | F10: =(Inputs!$C$162-Inputs!$C$163+Inputs!$C$164)/Inputs!$C$112 -> 880.83652 | G10: LTM PBT | H10: =(Inputs!$C$165-Inputs!$C$166+Inputs!$C$167)/Inputs!$C$112 -> 502.05871 | I10: N/D | J10: =Inputs!$C$168*Inputs!$C$169/Inputs!$C$112 -> 6692.3803 | K10: N/D | L10: =IF(ISNUMBER(K10),J10-K10,J10) -> 6692.3803 | M10: =IF(ISNUMBER(L10),L10/F10,"N/D") -> 7.5977552 | N10: =IF(ISNUMBER(J10),J10/F10,"N/D") -> 7.5977552 | O10: =IF(AND(ISNUMBER(J10),ISNUMBER(I10)),J10/I10,"N/D") -> N/D | P10: =Inputs!$C$164/Inputs!$C$163-1 -> 0.017318436 | Q10: =IF(AND(ISNUMBER(M10),ISNUMBER(P10)),IF(P10>0,M10/(P10*100),"n.m."),"N/D") -> 4.3870909 | R10: Listed/audited; price x 149.88m shares reconciles to quoted cap
A12: Note: eToro revenue = net contribution (net of crypto cost of sales). Gross 'total revenues & income' ($13.8bn FY25) is not comparable. Its growth rate is shown in cols P/Q.
A13: eToro growth in col P = H1 26 vs H1 25 net contribution. IG and Plus500 = H1 26 growth; Webull = H1 26 vs H1 25; XTB = H1 26; Trading 212 = FY25; Swissquote = H1 26.
A14: Rank on scale (funded/active accounts, m): 1 = largest. eToro rank: | F14: =RANK(C4,C4:C10) -> 3
A15: Rank on revenue ($m), eToro: | F15: =RANK(F4,F4:F10) -> 2
A16: Rank on client assets ($bn, of those disclosed), eToro: | F16: =RANK(D4,D4:D10) -> 5
A17: Peer median EV/Revenue or Mcap/Revenue (listed peers ex-eToro) | F17: =MEDIAN(N5:N8,N10) -> 5.9701309
A18: Peer median P/E (IG, Plus500, XTB) | F18: =MEDIAN(O5,O6,O8) -> 11.865411
A19: Plus500 EV / LTM EBITDA (closest listed peer) | F19: =L6/H6 -> 7.253661
A20: IG Mcap / CY25 EBITDA (no cash adj.) | F20: =J5/H5 -> 8.303521
A23: Moat ratings (analyst inputs; Strong / Moderate / Weak) | B23: Network effects | C23: Switching costs | D23: Scale / cost | E23: Intangible / regulatory | F23: # Strong | G23: # Moderate | H23: Evidence basis
A24: eToro | B24: Moderate | C24: Weak | D24: Moderate | E24: Moderate | F24: =COUNTIF(B24:E24,"Strong") -> 0 | G24: =COUNTIF(B24:E24,"Moderate") -> 3 | H24: CopyTrader/Popular Investor social graph (self-reported); multi-licence incl. MiCA, ASIC, FCA; no tax-wrapper lock-in at scale
A25: IG Group | B25: Weak | C25: Moderate | D25: Moderate | E25: Moderate | F25: =COUNTIF(B25:E25,"Strong") -> 0 | G25: =COUNTIF(B25:E25,"Moderate") -> 3 | H25: ISA/SIPP via Freetrade; long-established brand (founded 1974); audited
A26: Plus500 | B26: Weak | C26: Weak | D26: Moderate | E26: Moderate | F26: =COUNTIF(B26:E26,"Strong") -> 0 | G26: =COUNTIF(B26:E26,"Moderate") -> 2 | H26: Proprietary tech, 41% EBITDA margin; US futures business (non-OTC >$100m revenue FY25); audited
A27: Webull | B27: Weak | C27: Weak | D27: Moderate | E27: Moderate | F27: =COUNTIF(B27:E27,"Strong") -> 0 | G27: =COUNTIF(B27:E27,"Moderate") -> 2 | H27: US broker-dealer; EEA licence; audited
A28: XTB | B28: Weak | C28: Weak | D28: Moderate | E28: Moderate | F28: =COUNTIF(B28:E28,"Strong") -> 0 | G28: =COUNTIF(B28:E28,"Moderate") -> 2 | H28: Scale economics shown by 58% EBITDA margin H1 26; audited
A29: Trading 212 | B29: Weak | C29: Moderate | D29: Moderate | E29: Weak | F29: =COUNTIF(B29:E29,"Strong") -> 0 | G29: =COUNTIF(B29:E29,"Moderate") -> 2 | H29: ISA/SIPP wrappers in UK; low-cost model; group metrics self-reported
A30: Swissquote | B30: Weak | C30: Moderate | D30: Moderate | E30: Moderate | F30: =COUNTIF(B30:E30,"Strong") -> 0 | G30: =COUNTIF(B30:E30,"Moderate") -> 3 | H30: Swiss banking licence; custody franchise; audited
A32: Sector count of 'Strong' ratings (all firms, all categories) | F32: =SUM(F24:F30) -> 0

Sheet Valuation & Scenarios
A1: eToro valuation: EV range, M&A cross-checks, bull/base/bear (US$m unless stated)
A3: EV range: share count x cash credit | B3: Basic 79.53m | C3: Basic 82.85m (20-F) | D3: Diluted (NI/EPS) | F3: Note
A4: Shares (m) | B4: =Inputs!$C$89 -> 79.53 | C4: =Inputs!$C$90 -> 82.85 | D4: ='Historical Build & Ratios'!B78 -> 91.37931 | F4: 70.04m cover figure rejected (does not reconcile with 20-F Cl B)
A5: Market cap at $26.40 | B5: =B4*Inputs!$C$88 -> 2099.592 | C5: =C4*Inputs!$C$88 -> 2187.24 | D5: =D4*Inputs!$C$88 -> 2412.4138
A6: EV, case A: 100% cash credit | B6: =B$5-Inputs!$C$93*Inputs!$C$187+Inputs!$C$94 -> 899.592 | C6: =C$5-Inputs!$C$93*Inputs!$C$187+Inputs!$C$94 -> 987.24 | D6: =D$5-Inputs!$C$93*Inputs!$C$187+Inputs!$C$94 -> 1212.4138 | F6: Cash split corporate vs regulatory N/D; debt assumed nil
A7: EV, case B: 50% cash credit (central) | B7: =B$5-Inputs!$C$93*Inputs!$C$188+Inputs!$C$94 -> 1499.592 | C7: =C$5-Inputs!$C$93*Inputs!$C$188+Inputs!$C$94 -> 1587.24 | D7: =D$5-Inputs!$C$93*Inputs!$C$188+Inputs!$C$94 -> 1812.4138
A8: EV, case C: 0% cash credit | B8: =B$5-Inputs!$C$93*Inputs!$C$189+Inputs!$C$94 -> 2099.592 | C8: =C$5-Inputs!$C$93*Inputs!$C$189+Inputs!$C$94 -> 2187.24 | D8: =D$5-Inputs!$C$93*Inputs!$C$189+Inputs!$C$94 -> 2412.4138
A9: EV / LTM NC, case A | B9: =B6/'Historical Build & Ratios'!E22 -> 0.96834446 | C9: =C6/'Historical Build & Ratios'!E22 -> 1.0626911 | D9: =D6/'Historical Build & Ratios'!E22 -> 1.3050741
A10: EV / LTM NC, case B | B10: =B7/'Historical Build & Ratios'!E22 -> 1.6142002 | C10: =C7/'Historical Build & Ratios'!E22 -> 1.7085468 | D10: =D7/'Historical Build & Ratios'!E22 -> 1.9509298
A11: EV / LTM NC, case C | B11: =B8/'Historical Build & Ratios'!E22 -> 2.260056 | C11: =C8/'Historical Build & Ratios'!E22 -> 2.3544026 | D11: =D8/'Historical Build & Ratios'!E22 -> 2.5967856
A12: EV / LTM adj. EBITDA, case A | B12: =B6/'Historical Build & Ratios'!E23 -> 2.5556591 | C12: =C6/'Historical Build & Ratios'!E23 -> 2.8046591 | D12: =D6/'Historical Build & Ratios'!E23 -> 3.4443574
A13: EV / LTM adj. EBITDA, case B | B13: =B7/'Historical Build & Ratios'!E23 -> 4.2602045 | C13: =C7/'Historical Build & Ratios'!E23 -> 4.5092045 | D13: =D7/'Historical Build & Ratios'!E23 -> 5.1489028
A14: EV / LTM adj. EBITDA, case C | B14: =B8/'Historical Build & Ratios'!E23 -> 5.96475 | C14: =C8/'Historical Build & Ratios'!E23 -> 6.21375 | D14: =D8/'Historical Build & Ratios'!E23 -> 6.8534483
A15: P/E on LTM GAAP NI | B15: =B5/'Historical Build & Ratios'!E24 -> 8.0505828 | C15: =C5/'Historical Build & Ratios'!E24 -> 8.3866564 | D15: =D5/'Historical Build & Ratios'!E24 -> 9.2500529
A16: EV per funded account ($), case B | B16: =B7/'Historical Build & Ratios'!K7 -> 350.37196 | C16: =C7/'Historical Build & Ratios'!K7 -> 370.85047 | D16: =D7/'Historical Build & Ratios'!K7 -> 423.46117
A17: Share price vs IPO price | B17: =Inputs!$C$88/Inputs!$C$95-1 -> -0.49230769
A18: Market cap vs 2023 round ($3.5bn) | B18: =B5/Inputs!$C$198-1 -> -0.40011657
A19: Market cap vs SPAC valuation | B19: =B5/Inputs!$C$99-1 -> -0.79811615
A21: Growth-adjusted and peer cross-check | B21: eToro (B, 79.53m) | C21: Plus500 | F21: Note
A22: EV / LTM revenue | B22: ='Peer Benchmark'!M4 -> 1.6142002 | C22: ='Peer Benchmark'!M6 -> 3.0153499
A23: EV / LTM EBITDA | B23: =B13 -> 4.2602045 | C23: ='Peer Benchmark'!F19 -> 7.253661
A24: Revenue growth (H1 26) | B24: ='Peer Benchmark'!P4 -> 0.14051522 | C24: ='Peer Benchmark'!P6 -> 0.12
A25: EV/Revenue / growth (pts) | B25: =B22/(B24*100) -> 0.11487725 | C25: =C22/(C24*100) -> 0.25127916
A26: EV/EBITDA / growth (pts) | B26: =B23/(B24*100) -> 0.30318456 | C26: =C23/(C24*100) -> 0.60447175
A27: eToro discount to Plus500 on EV/EBITDA | B27: =B23/C23-1 -> -0.41268216
A28: eToro case C (0% cash) EV/EBITDA vs Plus500 | B28: =B14/C23-1 -> -0.17769111
A29: P/E: eToro vs peer median (IG, Plus500, XTB) | B29: =B15 -> 8.0505828 | C29: ='Peer Benchmark'!F18 -> 11.865411
A31: M&A cross-checks | B31: Freetrade (IG) | C31: Saxo (JSS) | D31: TradeZero (eToro, pending) | E31: eToro today (B) | F31: Note
A32: Implied 100% value ($m) | B32: =Inputs!$C$174*Inputs!$C$110 -> 211.92 | C32: =Inputs!$C$179/Inputs!$C$180*Inputs!$C$111 -> 1846.3333 | D32: =Inputs!$C$102 -> 231 | E32: =B7 -> 1499.592
A33: Value / revenue (x) | B33: =Inputs!$C$174/Inputs!$C$175 -> 5.8181818 | C33: N/D | D33: =Inputs!$C$102/Inputs!$C$103 -> 2.8875 | E33: =B10 -> 1.6142002
A34: Value / net profit (x) | B34: n.m. | C34: =Inputs!$C$179/Inputs!$C$180/Inputs!$C$181 -> 13.425926 | D34: N/D | E34: =B15 -> 8.0505828
A35: Value per customer / funded account ($) | B35: =B32/Inputs!$C$176 -> 294.33333 | C35: =C32/Inputs!$C$182 -> 1230.8889 | D35: N/D | E35: =B16 -> 350.37196
A36: Value / client assets | B36: =Inputs!$C$174/Inputs!$C$177 -> 0.064 | C36: =C32/(Inputs!$C$183*Inputs!$C$111*1000) -> 0.012113617 | D36: N/D | E36: =B7/('Historical Build & Ratios'!K8*1000) -> 0.07810375 | F36: Share of client assets (%)
A37: eToro implied at Freetrade $/customer x 4.28m funded ($m) | B37: =B35*'Historical Build & Ratios'!K7 -> 1259.7467
A38: eToro implied at Saxo P/E x LTM NI ($m equity) | B38: =C34*'Historical Build & Ratios'!E24 -> 3501.4815
A39: TradeZero share consideration at today's price ($m) | B39: =Inputs!$C$104*Inputs!$C$88 -> 66
A40: TradeZero multiple vs eToro's own EV/NC (case B) | B40: =D33/B10 -> 1.7888116
A42: Scenarios (12-month forward from LTM Q2 26) | B42: Bear | C42: Base | D42: Bull | F42: Note
A43: LTM net contribution ($m) | B43: ='Historical Build & Ratios'!E22 -> 929 | C43: ='Historical Build & Ratios'!E22 -> 929 | D43: ='Historical Build & Ratios'!E22 -> 929
A44: NTM NC growth | B44: -0.1 | C44: 0.08 | D44: 0.15 | F44: Bear: crypto/volatility slump. Base: FY25-like growth. Bull: H1 26 pace sustained
A45: Adj. EBITDA margin | B45: 0.28 | C45: 0.34 | D45: 0.37 | F45: LTM margin ~38%; range 33-43% over 10 qtrs
A46: Exit EV / adj. EBITDA (x) | B46: 4 | C46: 6 | D46: 8 | F46: Plus500 ~7x EV/EBITDA; IG ~8x mcap/EBITDA
A47: Cash credit (% of $1.2bn) | B47: 0.5 | C47: 0.75 | D47: 1 | F47: Unresolved cash definition drives the range
A48: Shares (m) | B48: =Inputs!$C$89 -> 79.53 | C48: =Inputs!$C$89 -> 79.53 | D48: =Inputs!$C$89 -> 79.53
A49: NTM NC ($m) | B49: =B43*(1+B44) -> 836.1 | C49: =C43*(1+C44) -> 1003.32 | D49: =D43*(1+D44) -> 1068.35
A50: NTM adj. EBITDA ($m) | B50: =B49*B45 -> 234.108 | C50: =C49*C45 -> 341.1288 | D50: =D49*D45 -> 395.2895
A51: Implied EV ($m) | B51: =B50*B46 -> 936.432 | C51: =C50*C46 -> 2046.7728 | D51: =D50*D46 -> 3162.316 | F51: TradeZero not modelled (pending; up to $231m)
A52: Implied equity ($m) | B52: =B51+Inputs!$C$93*B47-Inputs!$C$94 -> 1536.432 | C52: =C51+Inputs!$C$93*C47-Inputs!$C$94 -> 2946.7728 | D52: =D51+Inputs!$C$93*D47-Inputs!$C$94 -> 4362.316
A53: Implied value per share ($) | B53: =B52/B48 -> 19.318899 | C53: =C52/C48 -> 37.052343 | D53: =D52/D48 -> 54.851201
A54: Return vs $26.40 | B54: =B53/Inputs!$C$88-1 -> -0.26822354 | C54: =C53/Inputs!$C$88-1 -> 0.40349782 | D54: =D53/Inputs!$C$88-1 -> 1.077697
A55: Probability weight | B55: 0.25 | C55: 0.5 | D55: 0.25
A56: Probability-weighted value per share ($) | C56: =SUMPRODUCT(B53:D53,B55:D55) -> 37.068696
A57: Probability-weighted return | C57: =C56/Inputs!$C$88-1 -> 0.40411728
C58: =IF(SUM(B55:D55)=1,"weights OK","CHECK WEIGHTS") -> weights OK

Sheet Audit Log
A1: # | B1: Sheet!Ref | C1: Severity | D1: Category | E1: Issue | F1: Suggested fix
A2: 1 | B2: README!A15 | C2: Critical | D2: Data access | E2: WebFetch was blocked by the egress proxy for all primary sources (investors.etoro.com, sec.gov, globenewswire). Every figure comes from search-engine summaries of those URLs. | F2: Re-verify every blue input against the 20-F and 6-K filings before any external use.
A3: 2 | B3: Inputs!CASH_ETOR / Valuation & Scenarios!B6:D8 | C3: Critical | D3: Valuation | E3: The $1.2bn 'cash, cash equivalents & short-term investments' has no disclosed split between free corporate cash and regulatory capital. EV swings from $0.90bn to $2.10bn (base share count) on this alone. | F3: Obtain entity-level regulatory capital requirements from the 20-F / Pillar 3 disclosures. Until then, use the case B central view and show the range.
A4: 3 | B4: Inputs!SH_* / Valuation & Scenarios!B4:D4 | C4: Warning | D4: Capital structure | E4: Share count conflicts: 70.04m (Feb 26 cover), 82.85m (20-F YE25: 68.65m A + 14.20m B), 79.53m (aggregator), ~91.4m diluted (Q2 NI $53m / EPS $0.58). Market cap ranges $2.10bn to $2.41bn. | F4: Take the basic count from the Q2 26 6-K. The 70.04m figure is rejected because it cannot be reconciled to the 20-F Class B count.
A5: 4 | B5: Historical Build & Ratios!B37 | C5: Warning | D5: Reporting / definitions | E5: Three incompatible Q2 26 'revenue' growth rates circulate: NC +9%, total revenues & income -24%, and FX News Group's 'revenues fall 11%'. The -11% ties to neither. | F5: Use net contribution as the only comparable top line. Treat gross crypto revenue (94% of FY25 total revenues) as a pass-through.
A6: 5 | B6: Inputs!CRYPTO_Q2_25 | C6: Info | D6: Press error | E6: CoinDesk headline says crypto revenue 'dropped 120%'. That is impossible; the recomputed decline is -29%. | F6: Disregard the headline percentage.
A7: 6 | B7: Historical Build & Ratios!F72 | C7: Warning | D7: Internal inconsistency | E7: Q4 25 funded accounts are stated as 3.85m in the Q4 release and 3.81m in the FY25 press coverage. | F7: Confirm in the 20-F. The build uses 3.85m.
A8: 7 | B8: Inputs!FA_Aug26 | C8: Warning | D8: Unexplained flat-line | E8: August 2026 funded accounts (4.28m) are identical to 30 June. AUA growth slowed to +3% YoY in August from +10% in June. | F8: Check the monthly metrics release. Treat Q3 26 account growth as unproven.
A9: 8 | B9: Historical Build & Ratios!K11 | C9: Warning | D9: Unexplained inflection | E9: Adj. EBITDA growth fell from +35% (Q1 26) to +9% (Q2 26). Q1 was boosted by a ~4x surge in commodities volumes, and management plans to raise marketing to 25% of NC by YE26. | F9: Model margins at 33-38%, not at the Q1 peak.
A10: 9 | B10: Historical Build & Ratios!K12 | C10: Info | D10: Base effect | E10: Q2 26 NI growth of +77% flatters: the Q2 25 base ($30.2m) included $15m of IPO costs. On an ex-IPO-cost base, growth is ~+17%. | F10: Present NI growth ex one-offs.
A11: 10 | B11: Historical Build & Ratios!B4 / B22 | C11: Warning | D11: Derived data | E11: Q2 24 NC, Q4 25 adj EBITDA and Q4 25 NI are derived (FY less other quarters), not disclosed. FY23 NC ($639m) is described in the press as 'revenue (total fees)'. | F11: Replace with disclosed figures from the F-1 / 20-F.
A12: 11 | B12: Historical Build & Ratios!B13:K13 | C12: Info | D12: Non-statutory measures | E12: Adj. EBITDA and net contribution are non-GAAP. The GAAP equivalent of NC (total revenues & income) is dominated by gross crypto sales. | F12: Anchor profitability tests on GAAP NI where possible (done in the Scorecard).
A13: 12 | B13: Historical Build & Ratios!B40 | C13: Warning | D13: Cyclicality | E13: Earnings mix swings with retail activity: crypto went from 50% of trading commission (Q4 24) to 11% (Q2 26); commodities were 60% in Q1 26 and equities 60% in Q2 26. NII ($49m, 21% of NC) is rate-sensitive. | F13: Stress NC against a low-volatility, falling-rate scenario (bear case).
... A25: 24 | B25: Historical Build & Ratios!B16:K16 | C25: Info | D25: Model limitation | E25: The take-rate uses period-end AUA, not average AUA, and is only available for 5 quarters. | F25: Replace with average AUA from the filings.

Sheet Buffett Scorecard
A1: Earnings-durability scorecard: one investor's published framework (Warren Buffett's shareholder letters). Not a claim about what Buffett would conclude.
A3: # | B3: Test | C3: Metric | D3: Value | E3: Secondary value | F3: PASS / CAUTION thresholds | G3: Verdict | H3: Evidence / comment
A4: 1 | B4: Consistent operating history | C4: Profitable quarters / disclosed quarters (secondary = # quarters) | D4: ='Historical Build & Ratios'!D35 -> 1 | E4: ='Historical Build & Ratios'!C35 -> 10 | F4: PASS >= 90% over >= 12 qtrs; CAUTION if <12 qtrs; FAIL < 75% | G4: =IF(D4<0.75,"FAIL",IF(E4>=12,"PASS","CAUTION")) -> CAUTION | H4: Profitable in 10 of 10 disclosed quarters, but the disclosed history is short (FY23 NI only $15.3m; pre-2023 N/D; failed SPAC period).
A5: 2 | B5: Stable, predictable margins | C5: STDEVP adj. EBITDA margin: full 10 qtrs (secondary = last 5) | D5: ='Historical Build & Ratios'!B33 -> 0.038628111 | E5: ='Historical Build & Ratios'!B34 -> 0.030270918 | F5: PASS < 3pp; CAUTION 3-6pp; FAIL > 6pp (on the higher of the two) | G5: =IF(MAX(D5,E5)>0.06,"FAIL",IF(MAX(D5,E5)>0.03,"CAUTION","PASS")) -> CAUTION | H5: Margins ranged 33-43% on NC. Swings track retail volume regimes (crypto Q4 24, commodities Q1 26).
A6: 3 | B6: Self-funded growth | C6: Cumulative GAAP NI FY23-H1 26 / external capital raised since 2023 (2023 round + IPO primary) | D6: ='Historical Build & Ratios'!B36/(Inputs!$C$98+Inputs!$C$97) -> 0.99696429 | E6: =Inputs!$C$98+Inputs!$C$97 -> 560 | F6: PASS >= 1.5x; CAUTION 0.75-1.5x; FAIL < 0.75x | G6: =IF(D6>=1.5,"PASS",IF(D6>=0.75,"CAUTION","FAIL")) -> CAUTION | H6: Earnings since 2023 roughly equal the capital raised since 2023. Pre-2023 raises N/D. A $50m buyback in Feb 26 is a positive offset.
A7: 4 | B7: Organic compounding | C7: Upper-bound acquired share of funded-account growth, Q3 24-Q2 26 (Spaceship clients / account growth) | D7: =Inputs!$C$106/('Historical Build & Ratios'!K7-'Historical Build & Ratios'!D7) -> 0.18691589 | E7: ='Historical Build & Ratios'!K7-'Historical Build & Ratios'!D7 -> 1.07 | F7: PASS < 10%; CAUTION 10-30%; FAIL > 30% | G7: =IF(D7>0.3,"FAIL",IF(D7>0.1,"CAUTION","PASS")) -> CAUTION | H7: The Spaceship (AU) contribution is undisclosed, so an upper bound is used. TradeZero (pending) would add inorganic US accounts from H1 27.
A8: 5 | B8: Durable, behavioural moat | C8: # 'Strong' moat ratings for eToro (secondary = # Moderate) | D8: ='Peer Benchmark'!F24 -> 0 | E8: ='Peer Benchmark'!G24 -> 3 | F8: PASS >= 2 Strong; CAUTION 1 Strong or >= 2 Moderate; else FAIL | G8: =IF(D8>=2,"PASS",IF(OR(D8=1,E8>=2),"CAUTION","FAIL")) -> CAUTION | H8: No Strong rating for eToro, or for anyone in the sector. The social/copy network effect rests on self-reported engagement data.
A9: 6 | B9: Rational, aligned management | C9: CEO voting power (secondary = # reversed decisions) | D9: =Inputs!$C$101 -> 0.0934 | E9: =Inputs!$C$108 -> 1 | F9: PASS >= 10% and 0 reversals; CAUTION >= 5%; else FAIL | G9: =IF(AND(D9>=0.1,E9=0),"PASS",IF(D9>=0.05,"CAUTION","FAIL")) -> CAUTION | H9: Founder CEO holds 9.3% of votes. SPAC at $10.4bn abandoned in 2022. Buyback at ~$30 then share-funded TradeZero at 2.9x revenue, above eToro's own multiple.
A10: 7 | B10: Simple, predictable business | C10: Count of concurrent forward initiatives | D10: =Inputs!$C$107 -> 8 | F10: PASS <= 3; CAUTION 4-5; FAIL >= 6 | G10: =IF(D10>=6,"FAIL",IF(D10>=4,"CAUTION","PASS")) -> FAIL | H10: TradeZero/US; app migration; tokenisation/24-5; futures & US commodities; marketing ramp; eToro Money; AI agents; ASIC litigation.
A11: 8 | B11: Wonderful company at a fair price | C11: EV/LTM adj. EBITDA, case B, vs Plus500 (secondary = case C, 0% cash) | D11: ='Valuation & Scenarios'!B13/'Valuation & Scenarios'!C23 -> 0.58731784 | E11: ='Valuation & Scenarios'!B14/'Valuation & Scenarios'!C23 -> 0.82230889 | F11: PASS < 0.8x of peer; CAUTION 0.8-1.1x; FAIL > 1.1x | G11: =IF(D11<0.8,"PASS",IF(D11<=1.1,"CAUTION","FAIL")) -> PASS | H11: Price test passes even with zero cash credit, but on the growth-adjusted view the discount is smaller. It is a fair price for a cyclical business, not proof of a wonderful company.
B13: Tally | C13: PASS | D13: =COUNTIF(G4:G11,"PASS") -> 1
C14: CAUTION | D14: =COUNTIF(G4:G11,"CAUTION") -> 6
C15: FAIL | D15: =COUNTIF(G4:G11,"FAIL") -> 1
